README
setup.py
contentlet/__init__.py
contentlet/configuration.py
contentlet/expression.py
contentlet/interfaces.py
contentlet/provider.py
contentlet/zcml.py
contentlet.egg-info/PKG-INFO
contentlet.egg-info/SOURCES.txt
contentlet.egg-info/dependency_links.txt
contentlet.egg-info/top_level.txt
contentlet.egg-info/zip-safe
contentlet/tests/__init__.py
contentlet/tests/test_configuration.py
contentlet/tests/test_expression.py
contentlet/tests/test_provider.py
contentlet/tests/test_zcml.py