Metadata-Version: 1.0
Name: contentlet
Version: 0.1.1
Summary: Framework for reusable and composable UI with repoze.bfg.
Home-page: http://packages.python.org/contentlet
Author: Andrey Popp
Author-email: 8mayday@gmail.com
License: BSD
Keywords: web wsgi bfg ui
Platform: UNKNOWN
Classifier: Development Status :: 3 - Alpha
Classifier: Environment :: Web Environment
Classifier: Framework :: BFG
Classifier: Intended Audience :: Developers
Classifier: License :: OSI Approved :: BSD License
Classifier: Operating System :: OS Independent
Classifier: Programming Language :: Python
Classifier: Topic :: Internet :: WWW/HTTP :: Dynamic Content
Classifier: Topic :: Software Development :: Libraries :: Python Modules
